{
  "portal_1_white_checkered_panel": {
    "map_color": "color_light_gray"
  },
  "portal_1_white_half_panel": {
    "map_color": "color_light_gray"
  },
  "portal_1_white_panel": {
    "map_color": "color_light_gray"
  },
  "portal_1_white_2x1_panel_bottom": {
    "type": "pillar",
    "map_color": "color_light_gray"
  },
  "portal_1_white_2x1_panel_top": {
    "type": "pillar",
    "map_color": "color_light_gray"
  },
  "dirty_portal_1_white_checkered_panel": {
    "map_color": "terracotta_white"
  },
  "dirty_portal_1_white_half_panel": {
    "map_color": "terracotta_white"
  },
  "dirty_portal_1_white_panel": {
    "map_color": "terracotta_white"
  },
  "dirty_portal_1_white_2x1_panel_bottom": {
    "type": "pillar",
    "map_color": "terracotta_white"
  },
  "dirty_portal_1_white_2x1_panel_top": {
    "type": "pillar",
    "map_color": "terracotta_white"
  },
  "dirty_borderless_panel": {
    "map_color": "terracotta_white"
  },
  "portal_1_elevator_wall_bottom": {
    "map_color": "clay"
  },
  "portal_1_elevator_wall_middle": {
    "map_color": "clay"
  },
  "portal_1_elevator_wall_top": {
    "map_color": "clay"
  },
  "solid_office_concrete": {
    "map_color": "terracotta_cyan"
  },
  "bordered_office_concrete": {
    "map_color": "terracotta_brown"
  },
  "portal_1_smooth_tiles": {
    "map_color": "terracotta_light_gray"
  },
  "portal_1_smooth_gray_half_panel": {
    "map_color": "terracotta_brown",
  "sounds": {
    "break": "minecraft:block.copper.break",
    "step": "minecraft:block.copper.step",
    "place": "minecraft:block.copper.place",
    "hit": "minecraft:block.copper.hit",
    "fall": "minecraft:block.copper.fall"
  }},
  "portal_1_smooth_gray_panel": {
    "map_color": "terracotta_brown",
  "sounds": {
    "break": "minecraft:block.copper.break",
    "step": "minecraft:block.copper.step",
    "place": "minecraft:block.copper.place",
    "hit": "minecraft:block.copper.hit",
    "fall": "minecraft:block.copper.fall"
  }},
  "portal_1_smooth_gray_2x1_panel_bottom": {
    "map_color": "terracotta_brown",
  "type": "pillar",
    "sounds": {
      "break": "minecraft:block.copper.break",
      "step": "minecraft:block.copper.step",
      "place": "minecraft:block.copper.place",
      "hit": "minecraft:block.copper.hit",
      "fall": "minecraft:block.copper.fall"
    }
  },
  "portal_1_smooth_gray_2x1_panel_top": {
    "map_color": "terracotta_brown",
    "type": "pillar",
    "sounds": {
      "break": "minecraft:block.copper.break",
      "step": "minecraft:block.copper.step",
      "place": "minecraft:block.copper.place",
      "hit": "minecraft:block.copper.hit",
      "fall": "minecraft:block.copper.fall"
    }
  },
  "portal_1_smooth_gray_2x1_joiner": {
    "map_color": "terracotta_brown",
    "type": "pillar",
    "sounds": {
      "break": "minecraft:block.copper.break",
      "step": "minecraft:block.copper.step",
      "place": "minecraft:block.copper.place",
      "hit": "minecraft:block.copper.hit",
      "fall": "minecraft:block.copper.fall"
    }
  },
  "portal_1_smooth_gray_2x2_panel_bottom_left": {
    "map_color": "terracotta_brown",
  "type": "directional",
    "sounds": {
      "break": "minecraft:block.copper.break",
      "step": "minecraft:block.copper.step",
      "place": "minecraft:block.copper.place",
      "hit": "minecraft:block.copper.hit",
      "fall": "minecraft:block.copper.fall"
    }
  },
  "portal_1_smooth_gray_2x2_panel_bottom_right": {
    "map_color": "terracotta_brown",
  "type": "directional",
    "sounds": {
      "break": "minecraft:block.copper.break",
      "step": "minecraft:block.copper.step",
      "place": "minecraft:block.copper.place",
      "hit": "minecraft:block.copper.hit",
      "fall": "minecraft:block.copper.fall"
    }
  },
  "portal_1_smooth_gray_2x2_panel_top_left": {
    "map_color": "terracotta_brown",
  "type": "directional",
    "sounds": {
      "break": "minecraft:block.copper.break",
      "step": "minecraft:block.copper.step",
      "place": "minecraft:block.copper.place",
      "hit": "minecraft:block.copper.hit",
      "fall": "minecraft:block.copper.fall"
    }
  },
  "portal_1_smooth_gray_2x2_panel_top_right": {
    "map_color": "terracotta_brown",
  "type": "directional",
    "sounds": {
      "break": "minecraft:block.copper.break",
      "step": "minecraft:block.copper.step",
      "place": "minecraft:block.copper.place",
      "hit": "minecraft:block.copper.hit",
      "fall": "minecraft:block.copper.fall"
    }
  },

  "dirty_portal_1_smooth_gray_half_panel": {
    "map_color": "terracotta_green",
    "sounds": {
      "break": "minecraft:block.copper.break",
      "step": "minecraft:block.copper.step",
      "place": "minecraft:block.copper.place",
      "hit": "minecraft:block.copper.hit",
      "fall": "minecraft:block.copper.fall"
    }},
  "dirty_portal_1_smooth_gray_panel": {
    "map_color": "terracotta_green",
    "sounds": {
      "break": "minecraft:block.copper.break",
      "step": "minecraft:block.copper.step",
      "place": "minecraft:block.copper.place",
      "hit": "minecraft:block.copper.hit",
      "fall": "minecraft:block.copper.fall"
    }},
  "dirty_portal_1_smooth_gray_2x1_panel_bottom": {
    "map_color": "terracotta_green",
    "type": "pillar",
    "sounds": {
      "break": "minecraft:block.copper.break",
      "step": "minecraft:block.copper.step",
      "place": "minecraft:block.copper.place",
      "hit": "minecraft:block.copper.hit",
      "fall": "minecraft:block.copper.fall"
    }
  },
  "dirty_portal_1_smooth_gray_2x1_panel_top": {
    "map_color": "terracotta_green",
    "type": "pillar",
    "sounds": {
      "break": "minecraft:block.copper.break",
      "step": "minecraft:block.copper.step",
      "place": "minecraft:block.copper.place",
      "hit": "minecraft:block.copper.hit",
      "fall": "minecraft:block.copper.fall"
    }
  },
  "dirty_portal_1_smooth_gray_2x1_joiner": {
    "map_color": "terracotta_green",
    "type": "pillar",
    "sounds": {
      "break": "minecraft:block.copper.break",
      "step": "minecraft:block.copper.step",
      "place": "minecraft:block.copper.place",
      "hit": "minecraft:block.copper.hit",
      "fall": "minecraft:block.copper.fall"
    }
  },
  "dirty_portal_1_smooth_gray_2x2_panel_bottom_left": {
    "map_color": "terracotta_green",
    "type": "directional",
    "sounds": {
      "break": "minecraft:block.copper.break",
      "step": "minecraft:block.copper.step",
      "place": "minecraft:block.copper.place",
      "hit": "minecraft:block.copper.hit",
      "fall": "minecraft:block.copper.fall"
    }
  },
  "dirty_portal_1_smooth_gray_2x2_panel_bottom_right": {
    "map_color": "terracotta_green",
    "type": "directional",
    "sounds": {
      "break": "minecraft:block.copper.break",
      "step": "minecraft:block.copper.step",
      "place": "minecraft:block.copper.place",
      "hit": "minecraft:block.copper.hit",
      "fall": "minecraft:block.copper.fall"
    }
  },
  "dirty_portal_1_smooth_gray_2x2_panel_top_left": {
    "map_color": "terracotta_green",
    "type": "directional",
    "sounds": {
      "break": "minecraft:block.copper.break",
      "step": "minecraft:block.copper.step",
      "place": "minecraft:block.copper.place",
      "hit": "minecraft:block.copper.hit",
      "fall": "minecraft:block.copper.fall"
    }
  },
  "dirty_portal_1_smooth_gray_2x2_panel_top_right": {
    "map_color": "terracotta_green",
    "type": "directional",
    "sounds": {
      "break": "minecraft:block.copper.break",
      "step": "minecraft:block.copper.step",
      "place": "minecraft:block.copper.place",
      "hit": "minecraft:block.copper.hit",
      "fall": "minecraft:block.copper.fall"
    }
  },

  "portal_1_rusted_plating": {
    "map_color": "terracotta_brown",
    "sounds": {
      "break": "minecraft:block.copper.break",
      "step": "minecraft:block.copper.step",
      "place": "minecraft:block.copper.place",
      "hit": "minecraft:block.copper.hit",
      "fall": "minecraft:block.copper.fall"
    }
  },
  "portal_1_rusted_tread_plating": {
    "map_color": "terracotta_brown",
    "sounds": {
      "break": "minecraft:block.copper.break",
      "step": "minecraft:block.copper.step",
      "place": "minecraft:block.copper.place",
      "hit": "minecraft:block.copper.hit",
      "fall": "minecraft:block.copper.fall"
    }
  },
  "portal_1_metal_grating": {
    "map_color": "sand",
    "type": "old_ap",
    "render_layer": "cutout",
    "opaque": false,
    "sounds": {
      "break": "minecraft:block.lantern.break",
      "step": "minecraft:block.lantern.step",
      "place": "minecraft:block.lantern.place",
      "hit": "minecraft:block.lantern.hit",
      "fall": "minecraft:block.lantern.fall"
    }
  },
  "portal_1_mesh_grating": {
    "map_color": "color_black",
    "type": "old_ap",
    "render_layer": "cutout",
    "opaque": false,
    "sounds": {
      "break": "minecraft:block.vine.break",
      "step": "minecraft:block.vine.step",
      "place": "minecraft:block.vine.place",
      "hit": "minecraft:block.vine.hit",
      "fall": "minecraft:block.vine.fall"
    }
  },
  "portal_1_2x2_exposed_panel_bottom_left": {
    "map_color": "color_gray",
    "type": "directional"
  },
  "portal_1_2x2_exposed_panel_bottom_right": {
    "map_color": "color_gray",
    "type": "directional"
  },
  "portal_1_2x2_exposed_panel_top_left": {
    "map_color": "color_gray",
    "type": "directional"
  },
  "portal_1_2x2_exposed_panel_top_right": {
    "map_color": "color_gray",
    "type": "directional"
  },
  "sewage": {
    "inherit": "minecraft:mud",
    "map_color": "color_brown",
    "jump_velocity_multiplier": 0.05,
    "slipperiness": 0.999,
    "sounds": {
      "break": "minecraft:block.mud.break",
      "step": "portalcubed:sewage_step",
      "place": "minecraft:block.mud.place",
      "hit": "minecraft:block.mud.hit",
      "fall": "minecraft:block.mud.fall"
    }
  },
  "white_checkered_panel": {
    "map_color": "wool"
  },
  "white_half_panel": {
    "map_color": "wool"
  },
  "white_panel": {
    "map_color": "wool"
  },
  "white_2x1_panel_bottom": {
    "type": "pillar",
    "map_color": "wool"
  },
  "white_2x1_panel_top": {
    "type": "pillar",
    "map_color": "wool"
  },
  "white_2x2_panel_bottom_left": {
    "type": "directional",
    "map_color": "wool"
  },
  "white_2x2_panel_bottom_right": {
    "type": "directional",
    "map_color": "wool"
  },
  "white_2x2_panel_top_left": {
    "type": "directional",
    "map_color": "wool"
  },
  "white_2x2_panel_top_right": {
    "type": "directional",
    "map_color": "wool"
  },
  "aged_white_checkered_panel": {
    "map_color": "grass"
  },
  "aged_white_half_panel": {
    "map_color": "grass"
  },
  "aged_white_panel": {
    "map_color": "grass"
  },
  "aged_white_2x1_panel_bottom": {
    "type": "pillar",
    "map_color": "grass"
  },
  "aged_white_2x1_panel_top": {
    "type": "pillar",
    "map_color": "grass"
  },
  "aged_white_2x2_panel_bottom_left": {
    "type": "directional",
    "map_color": "grass"
  },
  "aged_white_2x2_panel_bottom_right": {
    "type": "directional",
    "map_color": "grass"
  },
  "aged_white_2x2_panel_top_left": {
    "type": "directional",
    "map_color": "grass"
  },
  "aged_white_2x2_panel_top_right": {
    "type": "directional",
    "map_color": "grass"
  },
  "padded_gray_half_panel": {
    "map_color": "deepslate"
  },
  "padded_gray_panel": {
    "map_color": "deepslate"
  },
  "padded_gray_2x1_panel_bottom": {
    "type": "pillar",
    "map_color": "deepslate"
  },
  "padded_gray_2x1_panel_top": {
    "type": "pillar",
    "map_color": "deepslate"
  },
  "padded_gray_2x2_panel_bottom_left": {
    "type": "directional",
    "map_color": "deepslate"
  },
  "padded_gray_2x2_panel_bottom_right": {
    "type": "directional",
    "map_color": "deepslate"
  },
  "padded_gray_2x2_panel_top_left": {
    "type": "directional",
    "map_color": "deepslate"
  },
  "padded_gray_2x2_panel_top_right": {
    "type": "directional",
    "map_color": "deepslate"
  },
  "aged_padded_gray_half_panel": {
    "map_color": "deepslate"
  },
  "aged_padded_gray_panel": {
    "map_color": "deepslate"
  },
  "aged_padded_gray_2x1_panel_bottom": {
    "map_color": "deepslate",
    "type": "pillar"
  },
  "aged_padded_gray_2x1_panel_top": {
    "type": "pillar",
    "map_color": "deepslate"
  },
  "aged_padded_gray_2x2_panel_bottom_left": {
    "type": "directional",
    "map_color": "deepslate"
  },
  "aged_padded_gray_2x2_panel_bottom_right": {
    "type": "directional",
    "map_color": "deepslate"
  },
  "aged_padded_gray_2x2_panel_top_left": {
    "type": "directional",
    "map_color": "deepslate"
  },
  "aged_padded_gray_2x2_panel_top_right": {
    "type": "directional",
    "map_color": "deepslate"
  },
  "smooth_gray_half_panel": {
    "map_color": "terracotta_cyan"
  },
  "smooth_gray_panel": {
    "map_color": "terracotta_cyan"
  },
  "smooth_gray_2x1_panel_bottom": {
    "type": "pillar",
    "map_color": "terracotta_cyan"
  },
  "smooth_gray_2x1_panel_top": {
    "type": "pillar",
    "map_color": "terracotta_cyan"
  },
  "smooth_gray_2x2_panel_bottom_left": {
    "type": "directional",
    "map_color": "terracotta_cyan"
  },
  "smooth_gray_2x2_panel_bottom_right": {
    "type": "directional",
    "map_color": "terracotta_cyan"
  },
  "smooth_gray_2x2_panel_top_left": {
    "type": "directional",
    "map_color": "terracotta_cyan"
  },
  "smooth_gray_2x2_panel_top_right": {
    "type": "directional",
    "map_color": "terracotta_cyan"
  },
  "aged_smooth_gray_half_panel": {
    "map_color": "terracotta_cyan"
  },
  "aged_smooth_gray_panel": {
    "map_color": "terracotta_cyan"
  },
  "aged_smooth_gray_2x1_panel_bottom": {
    "type": "pillar",
    "map_color": "terracotta_cyan"
  },
  "aged_smooth_gray_2x1_panel_top": {
    "type": "pillar",
    "map_color": "terracotta_cyan"
  },
  "aged_smooth_gray_2x2_panel_bottom_left": {
    "type": "directional",
    "map_color": "terracotta_cyan"
  },
  "aged_smooth_gray_2x2_panel_bottom_right": {
    "type": "directional",
    "map_color": "terracotta_cyan"
  },
  "aged_smooth_gray_2x2_panel_top_left": {
    "type": "directional",
    "map_color": "terracotta_cyan"
  },
  "aged_smooth_gray_2x2_panel_top_right": {
    "type": "directional",
    "map_color": "terracotta_cyan"
  },
  "insulation": {
    "map_color": "terracotta_yellow",
    "sounds": {
     "break": "minecraft:block.wool.break",
     "step": "minecraft:block.wool.step",
     "place": "minecraft:block.wool.place",
     "hit": "minecraft:block.wool.hit",
     "fall": "minecraft:block.wool.fall"
   }
  },
  "portal_2_panel_frame": {
    "render_layer": "cutout",
    "map_color": "none",
    "opaque": false,
    "sounds": {
      "break": "minecraft:block.lantern.break",
      "step": "minecraft:block.lantern.step",
      "place": "minecraft:block.lantern.place",
      "hit": "minecraft:block.lantern.hit",
      "fall": "minecraft:block.lantern.fall"
    }
  },
  "portal_2_panel_wireframe": {
    "opaque": false,
    "map_color": "none",
    "render_layer": "translucent",
    "sounds": {
      "break": "minecraft:block.lantern.break",
      "step": "minecraft:block.lantern.step",
      "place": "minecraft:block.lantern.place",
      "hit": "minecraft:block.lantern.hit",
      "fall": "minecraft:block.lantern.fall"
    }
  },
  "portal_2_exposed_panel": {
    "map_color": "terracotta_brown"
  },
  "portal_2_partially_exposed_panel": {
    "map_color": "terracotta_yellow"
  },
  "portal_2_metal_grating": {
    "type": "old_ap",
    "map_color": "color_light_gray",
    "render_layer": "cutout",
    "opaque": false,
    "sounds": {
      "break": "minecraft:block.lantern.break",
      "step": "minecraft:block.lantern.step",
      "place": "minecraft:block.lantern.place",
      "hit": "minecraft:block.lantern.hit",
      "fall": "minecraft:block.lantern.fall"
    }
  },
  "old_ap_white_checkered_panel": {
    "map_color": "sand",
  "sounds": {
    "break": "minecraft:block.wood.break",
    "step": "minecraft:block.wood.step",
    "place": "minecraft:block.wood.place",
    "hit": "minecraft:block.wood.hit",
    "fall": "minecraft:block.wood.fall"
  }},
  "old_ap_white_panel": {
    "map_color": "sand",
  "sounds": {
    "break": "minecraft:block.wood.break",
    "step": "minecraft:block.wood.step",
    "place": "minecraft:block.wood.place",
    "hit": "minecraft:block.wood.hit",
    "fall": "minecraft:block.wood.fall"
  }},
  "old_ap_white_2x2_panel_bottom_left": {
    "map_color": "sand",
    "type": "directional",
    "sounds": {
      "break": "minecraft:block.wood.break",
      "step": "minecraft:block.wood.step",
      "place": "minecraft:block.wood.place",
      "hit": "minecraft:block.wood.hit",
      "fall": "minecraft:block.wood.fall"
    }
  },
  "old_ap_white_2x2_panel_bottom_right": {
    "map_color": "sand",
    "type": "directional",
    "sounds": {
      "break": "minecraft:block.wood.break",
      "step": "minecraft:block.wood.step",
      "place": "minecraft:block.wood.place",
      "hit": "minecraft:block.wood.hit",
      "fall": "minecraft:block.wood.fall"
    }
  },
  "old_ap_white_2x2_panel_top_left": {
    "map_color": "sand",
    "type": "directional",
    "sounds": {
      "break": "minecraft:block.wood.break",
      "step": "minecraft:block.wood.step",
      "place": "minecraft:block.wood.place",
      "hit": "minecraft:block.wood.hit",
      "fall": "minecraft:block.wood.fall"
    }
  },
  "old_ap_white_2x2_panel_top_right": {
    "map_color": "sand",
    "type": "directional",
    "sounds": {
      "break": "minecraft:block.wood.break",
      "step": "minecraft:block.wood.step",
      "place": "minecraft:block.wood.place",
      "hit": "minecraft:block.wood.hit",
      "fall": "minecraft:block.wood.fall"
    }
  },
  "old_ap_green_panel": {
    "map_color": "terracotta_light_green",
    "sounds": {
      "break": "minecraft:block.netherite_block.break",
      "step": "minecraft:block.netherite_block.step",
      "place": "minecraft:block.netherite_block.place",
      "hit": "minecraft:block.netherite_block.hit",
      "fall": "minecraft:block.netherite_block.fall"
    }
  },
  "old_ap_green_2x1_panel_bottom": {
    "map_color": "terracotta_light_green",
    "type": "pillar",
    "sounds": {
      "break": "minecraft:block.netherite_block.break",
      "step": "minecraft:block.netherite_block.step",
      "place": "minecraft:block.netherite_block.place",
      "hit": "minecraft:block.netherite_block.hit",
      "fall": "minecraft:block.netherite_block.fall"
    }
  },
  "old_ap_green_2x1_panel_top": {
    "map_color": "terracotta_light_green",
    "type": "pillar",
    "sounds": {
      "break": "minecraft:block.netherite_block.break",
      "step": "minecraft:block.netherite_block.step",
      "place": "minecraft:block.netherite_block.place",
      "hit": "minecraft:block.netherite_block.hit",
      "fall": "minecraft:block.netherite_block.fall"
    }
  },
  "old_ap_green_2x2_panel_bottom_left": {
    "map_color": "terracotta_light_green",
    "type": "directional",
    "sounds": {
      "break": "minecraft:block.netherite_block.break",
      "step": "minecraft:block.netherite_block.step",
      "place": "minecraft:block.netherite_block.place",
      "hit": "minecraft:block.netherite_block.hit",
      "fall": "minecraft:block.netherite_block.fall"
    }
  },
  "old_ap_green_2x2_panel_bottom_right": {
    "map_color": "terracotta_light_green",
    "type": "directional",
    "sounds": {
      "break": "minecraft:block.netherite_block.break",
      "step": "minecraft:block.netherite_block.step",
      "place": "minecraft:block.netherite_block.place",
      "hit": "minecraft:block.netherite_block.hit",
      "fall": "minecraft:block.netherite_block.fall"
    }
  },
  "old_ap_green_2x2_panel_top_left": {
    "map_color": "terracotta_light_green",
    "type": "directional",
    "sounds": {
      "break": "minecraft:block.netherite_block.break",
      "step": "minecraft:block.netherite_block.step",
      "place": "minecraft:block.netherite_block.place",
      "hit": "minecraft:block.netherite_block.hit",
      "fall": "minecraft:block.netherite_block.fall"
    }
  },
  "old_ap_green_2x2_panel_top_right": {
    "map_color": "terracotta_light_green",
    "type": "directional",
    "sounds": {
      "break": "minecraft:block.netherite_block.break",
      "step": "minecraft:block.netherite_block.step",
      "place": "minecraft:block.netherite_block.place",
      "hit": "minecraft:block.netherite_block.hit",
      "fall": "minecraft:block.netherite_block.fall"
    }
  },
  "old_ap_blue_panel": {
    "map_color": "color_cyan",
    "sounds": {
      "break": "minecraft:block.netherite_block.break",
      "step": "minecraft:block.netherite_block.step",
      "place": "minecraft:block.netherite_block.place",
      "hit": "minecraft:block.netherite_block.hit",
      "fall": "minecraft:block.netherite_block.fall"
    }
  },
  "old_ap_blue_2x1_panel_bottom": {
    "map_color": "color_cyan",
    "type": "pillar",
    "sounds": {
      "break": "minecraft:block.netherite_block.break",
      "step": "minecraft:block.netherite_block.step",
      "place": "minecraft:block.netherite_block.place",
      "hit": "minecraft:block.netherite_block.hit",
      "fall": "minecraft:block.netherite_block.fall"
    }
  },
  "old_ap_blue_2x1_panel_top": {
    "map_color": "color_cyan",
    "type": "pillar",
    "sounds": {
      "break": "minecraft:block.netherite_block.break",
      "step": "minecraft:block.netherite_block.step",
      "place": "minecraft:block.netherite_block.place",
      "hit": "minecraft:block.netherite_block.hit",
      "fall": "minecraft:block.netherite_block.fall"
    }
  },
  "old_ap_blue_2x2_panel_bottom_left": {
    "map_color": "color_cyan",
    "type": "directional",
    "sounds": {
      "break": "minecraft:block.netherite_block.break",
      "step": "minecraft:block.netherite_block.step",
      "place": "minecraft:block.netherite_block.place",
      "hit": "minecraft:block.netherite_block.hit",
      "fall": "minecraft:block.netherite_block.fall"
    }
  },
  "old_ap_blue_2x2_panel_bottom_right": {
    "map_color": "color_cyan",
    "type": "directional",
    "sounds": {
      "break": "minecraft:block.netherite_block.break",
      "step": "minecraft:block.netherite_block.step",
      "place": "minecraft:block.netherite_block.place",
      "hit": "minecraft:block.netherite_block.hit",
      "fall": "minecraft:block.netherite_block.fall"
    }
  },
  "old_ap_blue_2x2_panel_top_left": {
    "map_color": "color_cyan",
    "type": "directional",
    "sounds": {
      "break": "minecraft:block.netherite_block.break",
      "step": "minecraft:block.netherite_block.step",
      "place": "minecraft:block.netherite_block.place",
      "hit": "minecraft:block.netherite_block.hit",
      "fall": "minecraft:block.netherite_block.fall"
    }
  },
  "old_ap_blue_2x2_panel_top_right": {
    "map_color": "color_cyan",
    "type": "directional",
    "sounds": {
      "break": "minecraft:block.netherite_block.break",
      "step": "minecraft:block.netherite_block.step",
      "place": "minecraft:block.netherite_block.place",
      "hit": "minecraft:block.netherite_block.hit",
      "fall": "minecraft:block.netherite_block.fall"
    }
  },
  "office_concrete": {
    "map_color": "terracotta_yellow"
  },
  "blue_office_concrete": {
    "map_color": "terracotta_cyan"
  },
  "striped_office_concrete": {
    "map_color": "metal"
  },
  "old_ap_metal_grating": {
    "map_color": "terracotta_yellow",
    "type": "old_ap",
    "render_layer": "cutout",
    "opaque": false,
    "sounds": {
      "break": "minecraft:block.lantern.break",
      "step": "minecraft:block.lantern.step",
      "place": "minecraft:block.lantern.place",
      "hit": "minecraft:block.lantern.hit",
      "fall": "minecraft:block.lantern.fall"
    }
  },
  "1x1_single_crossbar": {
    "map_color": "none",
    "type": "old_ap",
    "opaque": false,
    "render_layer": "cutout",
    "sounds": {
      "break": "minecraft:block.lantern.break",
      "step": "minecraft:block.lantern.step",
      "place": "minecraft:block.lantern.place",
      "hit": "minecraft:block.lantern.hit",
      "fall": "minecraft:block.lantern.fall"
    }
  },
  "1x1_double_crossbar": {
    "map_color": "none",
    "type": "old_ap",
    "opaque": false,
    "render_layer": "cutout",
    "sounds": {
      "break": "minecraft:block.lantern.break",
      "step": "minecraft:block.lantern.step",
      "place": "minecraft:block.lantern.place",
      "hit": "minecraft:block.lantern.hit",
      "fall": "minecraft:block.lantern.fall"
    }
  },
  "2x2_double_crossbar_bottom_left": {
    "map_color": "none",
    "type": "old_ap_directional",
    "opaque": false,
    "render_layer": "cutout",
    "sounds": {
      "break": "minecraft:block.lantern.break",
      "step": "minecraft:block.lantern.step",
      "place": "minecraft:block.lantern.place",
      "hit": "minecraft:block.lantern.hit",
      "fall": "minecraft:block.lantern.fall"
    }
  },
  "2x2_double_crossbar_bottom_right": {
    "map_color": "none",
    "type": "old_ap_directional",
    "opaque": false,
    "render_layer": "cutout",
    "sounds": {
      "break": "minecraft:block.lantern.break",
      "step": "minecraft:block.lantern.step",
      "place": "minecraft:block.lantern.place",
      "hit": "minecraft:block.lantern.hit",
      "fall": "minecraft:block.lantern.fall"
    }
  },
  "2x2_double_crossbar_top_left": {
    "map_color": "none",
    "type": "old_ap_directional",
    "opaque": false,
    "render_layer": "cutout",
    "sounds": {
      "break": "minecraft:block.lantern.break",
      "step": "minecraft:block.lantern.step",
      "place": "minecraft:block.lantern.place",
      "hit": "minecraft:block.lantern.hit",
      "fall": "minecraft:block.lantern.fall"
    }
  },
  "2x2_double_crossbar_top_right": {
    "map_color": "none",
    "type": "old_ap_directional",
    "opaque": false,
    "render_layer": "cutout",
    "sounds": {
      "break": "minecraft:block.lantern.break",
      "step": "minecraft:block.lantern.step",
      "place": "minecraft:block.lantern.place",
      "hit": "minecraft:block.lantern.hit",
      "fall": "minecraft:block.lantern.fall"
    }

  },
  "portal_1_white_half_panel_facade": {
    "type": "facade",
    "map_color": "color_light_gray"
  },
  "portal_1_white_panel_facade": {
    "type": "facade",
    "map_color": "color_light_gray"
  },
  "dirty_portal_1_white_half_panel_facade": {
    "type": "facade",
    "map_color": "terracotta_white"
  },
  "dirty_portal_1_white_panel_facade": {
    "type": "facade",
    "map_color": "terracotta_white"
  },
  "dirty_borderless_panel_facade": {
    "type": "facade",
    "map_color": "terracotta_white"
  },
  "portal_1_smooth_gray_half_panel_facade": {
    "type": "facade",
    "map_color": "terracotta_brown",
    "sounds": {
      "break": "minecraft:block.copper.break",
      "step": "minecraft:block.copper.step",
      "place": "minecraft:block.copper.place",
      "hit": "minecraft:block.copper.hit",
      "fall": "minecraft:block.copper.fall"
    }
  },
  "portal_1_smooth_gray_panel_facade": {
    "type": "facade",
    "map_color": "terracotta_brown",
    "sounds": {
      "break": "minecraft:block.copper.break",
      "step": "minecraft:block.copper.step",
      "place": "minecraft:block.copper.place",
      "hit": "minecraft:block.copper.hit",
      "fall": "minecraft:block.copper.fall"
    }
  },
  "dirty_portal_1_smooth_gray_half_panel_facade": {
    "type": "facade",
    "map_color": "terracotta_green",
    "sounds": {
      "break": "minecraft:block.copper.break",
      "step": "minecraft:block.copper.step",
      "place": "minecraft:block.copper.place",
      "hit": "minecraft:block.copper.hit",
      "fall": "minecraft:block.copper.fall"
    }
  },
  "dirty_portal_1_smooth_gray_panel_facade": {
    "type": "facade",
    "map_color": "terracotta_green",
    "sounds": {
      "break": "minecraft:block.copper.break",
      "step": "minecraft:block.copper.step",
      "place": "minecraft:block.copper.place",
      "hit": "minecraft:block.copper.hit",
      "fall": "minecraft:block.copper.fall"
    }
  },
  "portal_1_smooth_tile_facade": {
    "type": "facade",
    "map_color": "terracotta_light_gray"
  },
  "white_half_panel_facade": {
    "type": "facade",
    "map_color": "wool"
  },
  "white_panel_facade": {
    "type": "facade",
    "map_color": "wool"
  },
  "aged_white_half_panel_facade": {
    "type": "facade",
    "map_color": "grass"
  },
  "aged_white_panel_facade": {
    "type": "facade",
    "map_color": "grass"
  },
  "padded_gray_half_panel_facade": {
    "type": "facade",
    "map_color": "deepslate"
  },
  "padded_gray_panel_facade": {
    "type": "facade",
    "map_color": "deepslate"
  },
  "aged_padded_gray_half_panel_facade": {
    "type": "facade",
    "map_color": "deepslate"
  },
  "aged_padded_gray_panel_facade": {
    "type": "facade",
    "map_color": "deepslate"
  },
  "smooth_gray_half_panel_facade": {
    "type": "facade",
    "map_color": "terracotta_cyan"
  },
  "smooth_gray_panel_facade": {
    "type": "facade",
    "map_color": "terracotta_cyan"
  },
  "aged_smooth_gray_half_panel_facade": {
    "type": "facade",
    "map_color": "terracotta_cyan"
  },
  "aged_smooth_gray_panel_facade": {
    "type": "facade",
    "map_color": "terracotta_cyan"
  },
  "old_ap_white_checkered_panel_facade": {
    "type": "facade",
    "map_color": "sand",
    "sounds": {
      "break": "minecraft:block.wood.break",
      "step": "minecraft:block.wood.step",
      "place": "minecraft:block.wood.place",
      "hit": "minecraft:block.wood.hit",
      "fall": "minecraft:block.wood.fall"
    }
  },
  "old_ap_white_panel_facade": {
    "type": "facade",
    "map_color": "sand",
    "sounds": {
      "break": "minecraft:block.wood.break",
      "step": "minecraft:block.wood.step",
      "place": "minecraft:block.wood.place",
      "hit": "minecraft:block.wood.hit",
      "fall": "minecraft:block.wood.fall"
    }
  },
  "old_ap_green_panel_facade": {
    "type": "facade",
    "map_color": "terracotta_light_green",
    "sounds": {
      "break": "minecraft:block.netherite_block.break",
      "step": "minecraft:block.netherite_block.step",
      "place": "minecraft:block.netherite_block.place",
      "hit": "minecraft:block.netherite_block.hit",
      "fall": "minecraft:block.netherite_block.fall"
    }
  },
  "old_ap_blue_panel_facade": {
    "type": "facade",
    "map_color": "color_cyan",
    "sounds": {
      "break": "minecraft:block.netherite_block.break",
      "step": "minecraft:block.netherite_block.step",
      "place": "minecraft:block.netherite_block.place",
      "hit": "minecraft:block.netherite_block.hit",
      "fall": "minecraft:block.netherite_block.fall"
    }
  },
  "portal_1_rusted_plating_facade": {
    "type": "facade",
    "map_color": "terracotta_brown",
    "sounds": {
      "break": "minecraft:block.copper.break",
      "step": "minecraft:block.copper.step",
      "place": "minecraft:block.copper.place",
      "hit": "minecraft:block.copper.hit",
      "fall": "minecraft:block.copper.fall"
    }
  },
  "portal_1_rusted_tread_plating_side_facade": {
    "type": "facade",
    "map_color": "terracotta_brown",
    "sounds": {
      "break": "minecraft:block.copper.break",
      "step": "minecraft:block.copper.step",
      "place": "minecraft:block.copper.place",
      "hit": "minecraft:block.copper.hit",
      "fall": "minecraft:block.copper.fall"
    }
  },
  "portal_1_rusted_tread_plating_top_facade": {
    "type": "facade",
    "map_color": "terracotta_brown",
    "sounds": {
      "break": "minecraft:block.copper.break",
      "step": "minecraft:block.copper.step",
      "place": "minecraft:block.copper.place",
      "hit": "minecraft:block.copper.hit",
      "fall": "minecraft:block.copper.fall"
    }
  },
  "portal_1_mesh_grating_facade": {
    "type": "multiface",
    "map_color": "color_black",
    "render_layer": "cutout",
    "opaque": "false",
    "sounds": {
      "break": "minecraft:block.vine.break",
      "step": "minecraft:block.vine.step",
      "place": "minecraft:block.vine.place",
      "hit": "minecraft:block.vine.hit",
      "fall": "minecraft:block.vine.fall"
    }
  },
  "portal_1_metal_grating_facade": {
    "type": "multiface",
    "map_color": "sand",
    "render_layer": "cutout",
    "opaque": "false",
    "sounds": {
      "break": "minecraft:block.lantern.break",
      "step": "minecraft:block.lantern.step",
      "place": "minecraft:block.lantern.place",
      "hit": "minecraft:block.lantern.hit",
      "fall": "minecraft:block.lantern.fall"
    }
  },
  "portal_2_metal_grating_facade": {
    "type": "multiface",
    "map_color": "color_light_gray",
    "render_layer": "cutout",
    "opaque": "false",
    "sounds": {
      "break": "minecraft:block.lantern.break",
      "step": "minecraft:block.lantern.step",
      "place": "minecraft:block.lantern.place",
      "hit": "minecraft:block.lantern.hit",
      "fall": "minecraft:block.lantern.fall"
    }
  },
  "old_ap_metal_grating_facade": {
    "type": "multiface",
    "map_color": "terracotta_yellow",
    "render_layer": "cutout",
    "opaque": "false",
    "sounds": {
      "break": "minecraft:block.lantern.break",
      "step": "minecraft:block.lantern.step",
      "place": "minecraft:block.lantern.place",
      "hit": "minecraft:block.lantern.hit",
      "fall": "minecraft:block.lantern.fall"
    }
  },

  "exposed_panel_facade": {
    "type": "facade",
    "map_color": "terracotta_brown"
  },
  "partially_exposed_panel_facade": {
    "type": "facade",
    "map_color": "terracotta_yellow"
  },
  "insulation_facade": {
    "type": "facade",
    "map_color": "terracotta_yellow",
    "sounds": {
      "break": "minecraft:block.wool.break",
      "step": "minecraft:block.wool.step",
      "place": "minecraft:block.wool.place",
      "hit": "minecraft:block.wool.hit",
      "fall": "minecraft:block.wool.fall"
    }
  },



  "light_bridge": {
    "type": "provided",
    "render_layer": "translucent"
  },
  "light_bridge_emitter": {
    "type": "provided",
    "render_layer": "cutout"
  },
  "neurotoxin": {
    "type": "provided",
    "render_layer": "translucent"
  },
  "excursion_funnel": {
    "type": "provided",
    "render_layer": "translucent"
  },
  "excursion_funnel_emitter": {
    "type": "provided",
    "render_layer": "cutout"
  },
  "neurotoxin_emitter": {
    "type": "provided",
    "render_layer": "translucent"
  },
  "laser_emitter": {
    "type": "provided",
    "render_layer": "translucent"
  },
  "laser_catcher": {
    "type": "provided",
    "render_layer": "translucent"
  },
  "laser_relay": {
    "type": "provided",
    "render_layer": "translucent"
  },
  "conversion_gel": {
    "type": "provided",
    "render_layer": "translucent"
  },
  "reflection_gel": {
    "type": "provided",
    "render_layer": "translucent"
  },
  "propulsion_gel": {
    "type": "provided",
    "render_layer": "translucent"
  },
  "repulsion_gel": {
    "type": "provided",
    "render_layer": "translucent"
  },
  "adhesion_gel": {
    "type": "provided",
    "render_layer": "translucent"
  },
  "faith_plate": {
    "type": "provided",
    "render_layer": "translucent"
  },
  "beta_faith_plate": {
    "type": "provided",
    "render_layer": "translucent"
  },
  "faith_plate_target": {
    "type": "provided",
    "render_layer": "cutout"
  },
  "portal_1_door": {
    "type": "provided",
    "render_layer": "cutout"
  },
  "portal_2_door": {
    "type": "provided",
    "render_layer": "cutout"
  },
  "octopus_door": {
    "type": "provided",
    "render_layer": "cutout"
  },
  "old_ap_door": {
    "type": "provided",
    "render_layer": "cutout"
  },
  "fizzler": {
    "type": "provided",
    "render_layer": "translucent"
  },
  "pedestal_button": {
    "type": "provided",
    "render_layer": "cutout"
  },
  "floor_button": {
    "type": "provided",
    "render_layer": "cutout"
  },
  "old_ap_floor_button": {
    "type": "provided",
    "render_layer": "translucent"
  },
  "matter_inquisition_field": {
    "type": "provided",
    "render_layer": "translucent"
  },
  "physics_repulsion_field": {
    "type": "provided",
    "render_layer": "translucent"
  },
  "matter_inquisition_field_emitter": {
    "type": "provided",
    "render_layer": "translucent"
  },
  "physics_repulsion_field_emitter": {
    "type": "provided",
    "render_layer": "translucent"
  },
  "fizzler_emitter": {
    "type": "provided",
    "render_layer": "translucent"
  },
  "portal_1_fizzler": {
    "type": "provided",
    "render_layer": "cutout"
  },
  "portal_1_fizzler_emitter": {
    "type": "provided",
    "render_layer": "cutout"
  },
  "old_aperture_fizzler": {
    "type": "provided",
    "render_layer": "translucent"
  },
  "old_aperture_fizzler_emitter": {
    "type": "provided",
    "render_layer": "translucent"
  },
  "death_fizzler": {
    "type": "provided",
    "render_layer": "translucent"
  },
  "death_fizzler_emitter": {
    "type": "provided",
    "render_layer": "translucent"
  },
  "laser_fizzler": {
    "type": "provided",
    "render_layer": "translucent"
  },
  "laser_fizzler_emitter": {
    "type": "provided",
    "render_layer": "translucent"
  },
  "old_aperture_death_fizzler": {
    "type": "provided",
    "render_layer": "translucent"
  },
  "old_aperture_death_fizzler_emitter": {
    "type": "provided",
    "render_layer": "translucent"
  },
  "power_block": {
    "type": "provided",
    "render_layer": "cutout"
  },
  "rocket_turret": {
    "type": "provided",
    "render_layer": "cutout"
  },
  "catapult": {
    "type": "provided",
    "render_layer": "translucent"
  }
}
