{
	"credit": "Made with Blockbench by Cart3r.  ",
	"texture_size": [32, 32],
	"textures": {
		"0": "portalcubed:block/funnel_base",
		"1": "portalcubed:block/funnel_wings",
		"2": "portalcubed:block/funnel_wings_e",
		"3": "portalcubed:block/padded_gray_panel",
		"particle": "portalcubed:block/funnel_base"
	},
	"elements": [
		{
			"from": [0, 0, 0.025],
			"to": [16, 16, 15.025],
			"rotation": {"angle": 0, "axis": "z", "origin": [8, 1, 9.5]},
			"faces": {
				"north": {"uv": [6.984, 7.016, 0.016, 13.984], "rotation": 270, "texture": "#0"},
				"east": {"uv": [15.984, 0.016, 1, 16], "rotation": 180, "texture": "#3"},
				"south": {"uv": [6.984, 6.984, 0.016, 0.016], "rotation": 270, "texture": "#0"},
				"west": {"uv": [14.984, 0.016, 0, 16], "rotation": 180, "texture": "#3"},
				"up": {"uv": [0.016, 1.016, 16, 16], "rotation": 180, "texture": "#3"},
				"down": {"uv": [0.016, 0.016, 16, 15], "rotation": 180, "texture": "#3"}
			}
		},
		{
			"from": [1, 1, 15.775],
			"to": [15, 15, 15.775],
			"rotation": {"angle": 0, "axis": "z", "origin": [8, 1, 9.5]},
			"faces": {
				"north": {"uv": [6.984, 7.016, 0.016, 13.984], "rotation": 270, "texture": "#0"},
				"east": {"uv": [0.016, 0.016, 6.984, 0.016], "rotation": 270, "texture": "#0"},
				"south": {"uv": [6.984, 6.984, 0.016, 0.016], "rotation": 270, "texture": "#0"},
				"west": {"uv": [0.016, 0.016, 6.984, 0.016], "rotation": 90, "texture": "#0"},
				"up": {"uv": [0.016, 0.016, 6.984, 0.016], "rotation": 180, "texture": "#0"},
				"down": {"uv": [0.016, 0.016, 6.984, 0.016], "texture": "#0"}
			}
		},
		{
			"from": [2, 2, 15.075],
			"to": [14, 14, 15.525],
			"rotation": {"angle": 0, "axis": "z", "origin": [8, 1, 9.5]},
			"faces": {
				"north": {"uv": [15.984, 12.984, 10.016, 10.016], "rotation": 270, "texture": "#0"},
				"east": {"uv": [15.984, 12.984, 10.016, 10.016], "rotation": 270, "texture": "#0"},
				"south": {"uv": [15.984, 12.984, 10.016, 10.016], "rotation": 270, "texture": "#0"},
				"west": {"uv": [15.984, 12.984, 10.016, 10.016], "rotation": 90, "texture": "#0"},
				"up": {"uv": [15.984, 12.984, 10.016, 10.016], "rotation": 180, "texture": "#0"},
				"down": {"uv": [15.984, 12.984, 10.016, 10.016], "texture": "#0"}
			}
		},
		{
			"from": [0, 1, 15.025],
			"to": [1, 15, 17.025],
			"rotation": {"angle": 0, "axis": "z", "origin": [8, 1, 9.5]},
			"faces": {
				"north": {"uv": [7.984, 7.016, 7.516, 13.984], "texture": "#0"},
				"east": {"uv": [13.984, 6.016, 7.016, 6.984], "rotation": 270, "texture": "#0"},
				"south": {"uv": [7.484, 7.016, 7.016, 13.984], "texture": "#0"},
				"west": {"uv": [13.984, 5.016, 7.016, 5.984], "rotation": 90, "texture": "#0"},
				"up": {"uv": [0.016, 0.016, 0.484, 0.984], "rotation": 180, "texture": "#0"},
				"down": {"uv": [0.016, 0.016, 0.484, 0.984], "texture": "#0"}
			}
		},
		{
			"from": [15, 1.025, 15],
			"to": [16, 15.025, 17],
			"rotation": {"angle": 0, "axis": "z", "origin": [14, 1.025, 9.5]},
			"faces": {
				"north": {"uv": [7.984, 7.016, 7.516, 13.984], "texture": "#0"},
				"east": {"uv": [13.984, 5.016, 7.016, 5.984], "rotation": 270, "texture": "#0"},
				"south": {"uv": [7.484, 7.016, 7.016, 13.984], "texture": "#0"},
				"west": {"uv": [13.984, 6.016, 7.016, 6.984], "rotation": 90, "texture": "#0"},
				"up": {"uv": [0.016, 0.016, 0.484, 0.984], "rotation": 180, "texture": "#0"},
				"down": {"uv": [0.016, 0.016, 0.484, 0.984], "texture": "#0"}
			}
		},
		{
			"from": [3, 3, 15.025],
			"to": [13, 13, 16.025],
			"rotation": {"angle": 0, "axis": "z", "origin": [8, 1, 9.5]},
			"faces": {
				"east": {"uv": [8.016, 8.016, 12.984, 8.484], "rotation": 270, "texture": "#0"},
				"south": {"uv": [0.016, 5.016, 4.984, 9.984], "rotation": 270, "texture": "#1"},
				"west": {"uv": [8.016, 7.016, 12.984, 7.484], "rotation": 90, "texture": "#0"},
				"up": {"uv": [8.016, 7.516, 12.984, 7.984], "rotation": 180, "texture": "#0"},
				"down": {"uv": [8.016, 8.516, 12.984, 8.984], "texture": "#0"}
			}
		},
		{
			"from": [7, 7, 16.025],
			"to": [9, 9, 16.525],
			"rotation": {"angle": 0, "axis": "z", "origin": [8, 1, 9.5]},
			"faces": {
				"east": {"uv": [10.016, 9.016, 10.984, 9.484], "rotation": 270, "texture": "#0"},
				"south": {"uv": [8.984, 9.984, 8.016, 9.016], "rotation": 270, "texture": "#0"},
				"west": {"uv": [8.016, 10.016, 8.984, 10.484], "rotation": 90, "texture": "#0"},
				"up": {"uv": [9.016, 10.016, 9.984, 10.484], "rotation": 180, "texture": "#0"},
				"down": {"uv": [10.016, 9.516, 10.984, 9.984], "texture": "#0"}
			}
		},
		{
			"from": [2, 2, 15.025],
			"to": [14, 14, 20.025],
			"rotation": {"angle": 0, "axis": "z", "origin": [8, 1, 9.5]},
			"faces": {
				"east": {"uv": [0.016, 2.516, 5.984, 4.984], "rotation": 270, "texture": "#1"},
				"west": {"uv": [0.016, 0.016, 5.984, 2.484], "rotation": 90, "texture": "#1"},
				"up": {"uv": [6.016, 2.516, 11.984, 4.984], "rotation": 180, "texture": "#1"},
				"down": {"uv": [6.016, 0.016, 11.984, 2.484], "texture": "#1"}
			}
		},
		{
			"from": [14, 2, 15.025],
			"to": [2, 14, 20.025],
			"rotation": {"angle": 0, "axis": "z", "origin": [8, 1, 9.5]},
			"faces": {
				"east": {"uv": [0.016, 10.016, 5.984, 12.484], "rotation": 270, "texture": "#1"},
				"west": {"uv": [0.016, 12.516, 5.984, 14.984], "rotation": 90, "texture": "#1"},
				"up": {"uv": [6.016, 12.516, 11.984, 14.984], "rotation": 180, "texture": "#1"},
				"down": {"uv": [6.016, 10.016, 11.984, 12.484], "texture": "#1"}
			}
		},
		{
			"from": [2, 2, 15.025],
			"to": [14, 14, 20.025],
			"rotation": {"angle": 0, "axis": "z", "origin": [8, 1, 9.5]},
			"faces": {
				"east": {"uv": [0.016, 2.516, 5.984, 4.984], "rotation": 270, "texture": "#2"},
				"west": {"uv": [0.016, 0.016, 5.984, 2.484], "rotation": 90, "texture": "#2"},
				"up": {"uv": [6.016, 2.516, 11.984, 4.984], "rotation": 180, "texture": "#2"},
				"down": {"uv": [6.016, 0.016, 11.984, 2.484], "texture": "#2"}
			}
		},
		{
			"from": [14, 2, 15.025],
			"to": [2, 14, 20.025],
			"rotation": {"angle": 0, "axis": "z", "origin": [8, 1, 9.5]},
			"faces": {
				"east": {"uv": [0.016, 10.016, 5.984, 12.484], "rotation": 270, "texture": "#2"},
				"west": {"uv": [0.016, 12.516, 5.984, 14.984], "rotation": 90, "texture": "#2"},
				"up": {"uv": [6.016, 12.516, 11.984, 14.984], "rotation": 180, "texture": "#2"},
				"down": {"uv": [6.016, 10.016, 11.984, 12.484], "texture": "#2"}
			}
		},
		{
			"from": [0, 0, 15.025],
			"to": [16, 1, 17.025],
			"rotation": {"angle": 0, "axis": "z", "origin": [8, 1, 9.5]},
			"faces": {
				"north": {"uv": [7.984, 7.016, 7.516, 14.984], "rotation": 270, "texture": "#0"},
				"east": {"uv": [9.516, 9.016, 9.984, 9.984], "rotation": 270, "texture": "#0"},
				"south": {"uv": [7.484, 14.984, 7.016, 7.016], "rotation": 270, "texture": "#0"},
				"west": {"uv": [9.016, 9.016, 9.484, 9.984], "rotation": 90, "texture": "#0"},
				"up": {"uv": [7.016, 6.016, 14.984, 6.984], "rotation": 180, "texture": "#0"},
				"down": {"uv": [7.016, 5.016, 14.984, 5.984], "texture": "#0"}
			}
		},
		{
			"from": [0, 15, 15.025],
			"to": [16, 16, 17.025],
			"rotation": {"angle": 0, "axis": "z", "origin": [8, 1, 9.5]},
			"faces": {
				"north": {"uv": [7.984, 7.016, 7.516, 14.984], "rotation": 270, "texture": "#0"},
				"east": {"uv": [9.516, 9.016, 9.984, 9.984], "rotation": 270, "texture": "#0"},
				"south": {"uv": [7.484, 14.984, 7.016, 7.016], "rotation": 270, "texture": "#0"},
				"west": {"uv": [9.016, 9.016, 9.484, 9.984], "rotation": 90, "texture": "#0"},
				"up": {"uv": [7.016, 5.016, 14.984, 5.984], "rotation": 180, "texture": "#0"},
				"down": {"uv": [7.016, 6.016, 14.984, 6.984], "texture": "#0"}
			}
		}
	],
	"display": {
		"thirdperson_righthand": {
			"rotation": [75, 144, 0],
			"translation": [0, 2.5, 0],
			"scale": [0.375, 0.375, 0.375]
		},
		"thirdperson_lefthand": {
			"rotation": [75, 144, 0],
			"translation": [0, 2.5, 0],
			"scale": [0.375, 0.375, 0.375]
		},
		"firstperson_righthand": {
			"rotation": [10.5, -77.75, 0],
			"translation": [0, 1.75, 0],
			"scale": [0.4, 0.4, 0.4]
		},
		"firstperson_lefthand": {
			"rotation": [10.5, -77.75, 0],
			"translation": [0, 1.75, 0],
			"scale": [0.4, 0.4, 0.4]
		},
		"ground": {
			"translation": [0, 3, 0],
			"scale": [0.25, 0.25, 0.25]
		},
		"gui": {
			"rotation": [30, 48.75, 0],
			"scale": [0.55664, 0.55664, 0.55664]
		},
		"head": {
			"rotation": [178, 0, 0],
			"translation": [0, 0.5, -0.25],
			"scale": [0.91406, 0.91406, 0.91406]
		},
		"fixed": {
			"rotation": [0, -177, 0],
			"scale": [0.5, 0.5, 0.5]
		}
	}
}